pydmrs/__init__.py
pydmrs/_exceptions.py
pydmrs/components.py
pydmrs/core.py
pydmrs/pydelphin_interface.py
pydmrs/rooted.py
pydmrs/serial.py
pydmrs/utils.py
pydmrs/__config__/default_interface.conf
pydmrs/__config__/default_simplification.conf
pydmrs/graphlang/__init__.py
pydmrs/graphlang/graphlang.py
pydmrs/mapping/__init__.py
pydmrs/mapping/mapping.py
pydmrs/matching/__init__.py
pydmrs/matching/aligned_matching.py
pydmrs/matching/common.py
pydmrs/matching/exact_matching.py
pydmrs/matching/general_matching.py
pydmrs/matching/query.py
pydmrs/simplification/__init__.py
pydmrs/simplification/gpred_filtering.py
pydmrs-1.0.6.dist-info/DESCRIPTION.rst
pydmrs-1.0.6.dist-info/METADATA
pydmrs-1.0.6.dist-info/RECORD
pydmrs-1.0.6.dist-info/WHEEL
pydmrs-1.0.6.dist-info/metadata.json
pydmrs-1.0.6.dist-info/top_level.txt
