Metadata-Version: 2.0
Name: pydmrs
Version: 1.0.6
Summary: A library for manipulating DMRS graphs
Home-page: https://github.com/delph-in/pydmrs
Author: Ann Copestake, Guy Emerson, Mike Goodman, Matic Horvat, Alex Kuhnle, Ewa Muszyńska
Author-email: gete2@cam.ac.uk
License: MIT
Download-URL: https://github.com/delph-in/pydmrs/tarball/1.0.6
Keywords: NLP,Natural Language Processing,Computational Linguistics,Semantics
Platform: UNKNOWN
Requires-Dist: pydelphin
